LICENSE
MANIFEST.in
README.md
requirements.txt
setup.cfg
setup.py
pikepdf_annots/__init__.py
pikepdf_annots/forms.py
pikepdf_annots/matchers.py
pikepdf_annots.egg-info/PKG-INFO
pikepdf_annots.egg-info/SOURCES.txt
pikepdf_annots.egg-info/dependency_links.txt
pikepdf_annots.egg-info/requires.txt
pikepdf_annots.egg-info/top_level.txt
tests/__init__.py
tests/test_editable_form.py
tests/test_matcher_rect.py
tests/test_matcher_text.py
tests/data/10346E_Diver_Medical_Form.pdf