Metadata-Version: 2.1
Name: pikepdf-annots
Version: 0.0.1
Summary: PikePDF helper utilities
Home-page: https://github.com/DiveWithDamian/pikepdf-annots
Author: Damian Zaremba
Author-email: oss@divewithdamian.eu
License: MIT
Keywords: pikepdf pdf annots annotations
Platform: any
Classifier: Programming Language :: Python :: 3
Classifier: Operating System :: OS Independent
Requires-Python: >=3.9
